README.md
setup.py
libra_py_001_06/__init__.py
libra_py_001_06/base.py
libra_py_001_06/lbi.py
libra_py_001_06/linear.py
libra_py_001_06/logistic.py
libra_py_001_06.egg-info/PKG-INFO
libra_py_001_06.egg-info/SOURCES.txt
libra_py_001_06.egg-info/dependency_links.txt
libra_py_001_06.egg-info/requires.txt
libra_py_001_06.egg-info/top_level.txt