Metadata-Version: 1.1
Name: libra-py-001-06
Version: 0.0.1
Summary: Split Linearized Bregman Iteration
Home-page: https://github.com/tansey/smoothfdr
Author: Xinwei Sun
Author-email: sxwxiaoxiaohehe@pku.edu.cn
License: MIT
Keywords: sparsity regularization path Lasso variable-selection
Platform: UNKNOWN
Classifier: Development Status :: 1 - Planning
Classifier: Intended Audience :: Science/Research
Classifier: Topic :: Scientific/Engineering
Classifier: License :: Free For Educational Use
Classifier: Programming Language :: Python :: 2.7
Classifier: Programming Language :: Python :: 3.5
